MANIFEST.in
README.rst
setup.cfg
setup.py
ptcdt/__init__.py
ptcdt/client.py
ptcdt/contracts.py
ptcdt/converter.py
ptcdt/main.py
ptcdt/server.py
ptcdt/thrift_parser.py
ptcdt.egg-info/PKG-INFO
ptcdt.egg-info/SOURCES.txt
ptcdt.egg-info/dependency_links.txt
ptcdt.egg-info/entry_points.txt
ptcdt.egg-info/requires.txt
ptcdt.egg-info/top_level.txt