Metadata-Version: 2.1
Name: ptcdt
Version: 0.0.2
Summary: Tool for Thrift contract-consumer-driven testing
Home-page: https://github.com/vtatai/ptcdt/
Author: Victor Tatai
Author-email: vtatai@gmail.com
License: Apache License, V.2
Keywords: thrift python testing contract consumer
Platform: UNKNOWN
Requires-Python: >=3.2.*
Provides-Extra: dev
